README.md
setup.py
lipsync_seisei/__init__.py
lipsync_seisei/face_det.py
lipsync_seisei/video_gen.py
lipsync_seisei.egg-info/PKG-INFO
lipsync_seisei.egg-info/SOURCES.txt
lipsync_seisei.egg-info/dependency_links.txt
lipsync_seisei.egg-info/requires.txt
lipsync_seisei.egg-info/top_level.txt
lipsync_seisei/face_detection/__init__.py
lipsync_seisei/face_detection/face_alignment.py
lipsync_seisei/face_detection/models.py
lipsync_seisei/face_detection/utils.py
lipsync_seisei/face_detection/detection/__init__.py
lipsync_seisei/face_detection/detection/core.py
lipsync_seisei/face_detection/detection/sfd/__init__.py
lipsync_seisei/face_detection/detection/sfd/bbox.py
lipsync_seisei/face_detection/detection/sfd/detect.py
lipsync_seisei/face_detection/detection/sfd/net_s3fd.py
lipsync_seisei/face_detection/detection/sfd/sfd_detector.py
lipsync_seisei/video_generation/__init__.py
lipsync_seisei/video_generation/conv.py
lipsync_seisei/video_generation/wav2lip.py
lipsync_seisei/video_generation/audio_mod/__init__.py
lipsync_seisei/video_generation/audio_mod/audio.py
lipsync_seisei/video_generation/audio_mod/hparams.py