Metadata-Version: 2.2
Name: lipsync_seisei
Version: 0.0.2
Requires-Dist: pytest
Requires-Dist: setuptools
Requires-Dist: numpy
Requires-Dist: opencv-python
Requires-Dist: tqdm
Requires-Dist: torch
Requires-Dist: scipy
Requires-Dist: librosa
Dynamic: description
Dynamic: description-content-type
Dynamic: requires-dist
